cenerator/__init__.py
cenerator/identifier.py
cenerator/pack.py
cenerator/value.py
cenerator/warning.py
cenerator-0.1.4.dist-info/licenses/LICENSE
cenerator-0.1.4.dist-info/METADATA
cenerator-0.1.4.dist-info/WHEEL
cenerator-0.1.4.dist-info/top_level.txt
cenerator-0.1.4.dist-info/RECORD
