Metadata-Version: 2.4
Name: cenerator
Version: 0.1.4
Summary: A Minecraft data pack creation utility
Author-email: Zakru <me@zakru.fi>
License-Expression: MIT
Project-URL: Source Code, https://github.com/Zakru/cenerator
Project-URL: Issue Tracker, https://github.com/Zakru/cenerator/issues
Classifier: Development Status :: 3 - Alpha
Classifier: Intended Audience :: Developers
Classifier: Operating System :: OS Independent
Classifier: Programming Language :: Python :: 3
Classifier: Topic :: Games/Entertainment
Classifier: Topic :: Software Development :: Libraries
Requires-Python: >=3.9
License-File: LICENSE
Dynamic: license-file
